hifir4py-0.1.0.dist-info/METADATA
hifir4py-0.1.0.dist-info/WHEEL
hifir4py-0.1.0.dist-info/LICENSE
hifir4py-0.1.0.dist-info/RECORD
hifir4py-0.1.0.dist-info/top_level.txt
hifir4py.libs/libgfortran-139be63a.so.3.0.0
hifir4py.libs/libopenblasp-r0-0d9bff2c.3.3.so
hifir4py/__init__.py
hifir4py/file_dp.pyx
hifir4py/hif.py
hifir4py/utils.py
hifir4py/file_dp.cpython-39-x86_64-linux-gnu.so
hifir4py/__init__.pxd
hifir4py/hifir4py.hpp
hifir4py/ksp/gmres.py
hifir4py/ksp/orth_null.py
hifir4py/ksp/__init__.py
hifir4py/ksp/mul_crs_ax.cpython-39-x86_64-linux-gnu.so
hifir4py/ksp/mul_crs_ax.pyx
hifir4py/ksp/pipit.py
hifir4py/_hifir/si64hif.pyx
hifir4py/_hifir/params_helper.cpython-39-x86_64-linux-gnu.so
hifir4py/_hifir/params_helper.pyx
hifir4py/_hifir/di64hif.cpython-39-x86_64-linux-gnu.so
hifir4py/_hifir/ci64hif.cpython-39-x86_64-linux-gnu.so
hifir4py/_hifir/ci32hif.cpython-39-x86_64-linux-gnu.so
hifir4py/_hifir/di32hif.pyx
hifir4py/_hifir/zi32hif.cpython-39-x86_64-linux-gnu.so
hifir4py/_hifir/zi32hif.pyx
hifir4py/_hifir/di64hif.pyx
hifir4py/_hifir/si32hif.pyx
hifir4py/_hifir/__init__.py
hifir4py/_hifir/impl_pyhif.pxi
hifir4py/_hifir/zi64hif.cpython-39-x86_64-linux-gnu.so
hifir4py/_hifir/si64hif.cpython-39-x86_64-linux-gnu.so
hifir4py/_hifir/si32hif.cpython-39-x86_64-linux-gnu.so
hifir4py/_hifir/ci32hif.pyx
hifir4py/_hifir/zi64hif.pyx
hifir4py/_hifir/di32hif.cpython-39-x86_64-linux-gnu.so
hifir4py/_hifir/ci64hif.pyx
hifir4py/_hifir/utils.pyx
hifir4py/_hifir/utils.cpython-39-x86_64-linux-gnu.so
