Metadata-Version: 2.1
Name: hifir4py
Version: 0.1.0
Summary: HIFIR Python3 Interface
Home-page: UNKNOWN
Author: NumGeom Group at Stony Brook University
License: UNKNOWN
Platform: UNKNOWN
Classifier: Development Status :: 5 - Production/Stable
Classifier: Programming Language :: Python :: 3 :: Only
Classifier: Programming Language :: Python :: 3.6
Classifier: Programming Language :: Python :: 3.7
Classifier: Programming Language :: Python :: 3.8
Classifier: Programming Language :: Python :: 3.9
Classifier: Programming Language :: C++
Classifier: Programming Language :: Cython
Classifier: Topic :: Scientific/Engineering :: Mathematics
Classifier: Operating System :: POSIX
Classifier: Intended Audience :: Science/Research
Classifier: License :: OSI Approved :: GNU Affero General Public License v3 or later (AGPLv3+)
Requires-Python: >=3.6
License-File: LICENSE
Requires-Dist: Cython
Requires-Dist: numpy
Requires-Dist: scipy (>=1.5.1)
